CHANGES.rst
MANIFEST.in
README.rst
setup.py
alnair/__init__.py
alnair/command.py
alnair/distribution.py
alnair/exception.py
alnair/package.py
alnair.egg-info/PKG-INFO
alnair.egg-info/SOURCES.txt
alnair.egg-info/dependency_links.txt
alnair.egg-info/entry_points.txt
alnair.egg-info/not-zip-safe
alnair.egg-info/requires.txt
alnair.egg-info/top_level.txt
alnair/templates/common.py.template
alnair/templates/recipe.py.template